Workbook

Sheet Janeiro
A1: Contas - saidas | E1: Entradas | J1: Cartão
A2: Janeiro | C2: Status | E2: Janeiro | G2: Status | J2: Janeiro | M2: Totais mensal
A3: claro | B3: 119.41 | C3: ok | E3: salario | F3: 8500 | M3: saidas | P3: previsão de sobra
A4: desktop | B4: 109.99 | C4: ok | E4: vale | F4: 3320.58 | M4: =B19 -> 8952.85 | P4: 0
A5: maisa | B5: 500 | C5: ok | M5: Entradas
A6: juros obra | B6: 1373 | C6: ok | M6: =F18 -> 11820.58
A7: aP | B7: 1260.45 | C7: ok | M7: Sobrou do mes passado
A8: cartao nu | B8: 4500 | C8: ok | M8: 0
A9: cartao mercado pago | B9: 1035 | C9: ok | M9: Colocado na poupança
A10: celular vó | B10: 55 | C10: ok | M10: 0
E18: total | F18: =SUM(F3:F17) -> 11820.58 | J18: total | K18: =SUM(K3:K17) -> 0
A19: total | B19: =SUM(B3:B18) -> 8952.85
E21: Compras Recorrentes
E22: todo mes é isso
E23: amazon | F23: 19.9
E24: spotfy | F24: 21.9
E25: mercado livre | F25: 27.99
E26: apple | F26: 15
E34: Total | F34: =SUM(F23:F27) -> 84.79

Sheet Fevereiro
A1: Contas - saidas | E1: Entradas | J1: Cartão nu - Demonstrativo de parcelamentos
A2: Fevereiro | C2: Status | E2: Fevereiro | G2: Status | J2: Fevereiro | M2: Totais mensal
A3: claro | B3: 119.41 | C3: ok | E3: Salario | F3: 4500 | G3: ok | M3: saidas | P3: previsão de sobra
A4: desktop | B4: 109.99 | C4: ok | E4: Vale | F4: 3000 | M4: =B19 -> 6772.29 | P4: 0
A5: maisa | B5: 500 | C5: ok | M5: Entradas
A6: juros obra | B6: 1373 | C6: ok | M6: =F18 -> 7500 | P6: Total Poupança
A7: aP | B7: 1260.45 | C7: ok | M7: Sobrou do mes passado | P7: =M10+M12 -> 0
A8: cartao nu | B8: 1802.52 | C8: ok | M8: =Janeiro!P4 -> 0
A9: cartao mercado pago | B9: 1306.92 | C9: ok | M9: Colocado na poupança
A10: reforma muro | B10: 300 | C10: ok | M10: 0
M11: Poupança do mes anterior
M12: =Janeiro!M10 -> 0
E18: total | F18: =SUM(F3:F17) -> 7500 | J18: total | K18: =SUM(K3:K17) -> 0
A19: total | B19: =SUM(B3:B18) -> 6772.29
E21: Compras Recorrentes | J21: Cartão MP - parcelamentos | M21: Cartão Caixa - parcelamentos
E22: todo mes é isso | J22: Fevereiro | M22: Fevereiro
E34: Total | F34: =SUM(F23:F27) -> 0
J38: total | K38: =SUM(K23:K37) -> 0 | M38: total | N38: =SUM(N23:N37) -> 0

Sheet Março
A1: Contas - saidas | E1: Entradas | I1: Cartão nu - Demonstrativo de parcelamentos
A2: Fevereiro | C2: Status | E2: Fevereiro | G2: Status | I2: Fevereiro | L2: Totais mensal
A3: claro | B3: 119.41 | C3: ok | E3: Salario | F3: 4864.16 | G3: ok | I3: Ml 3/4 | J3: 26.65 | L3: saidas | O3: previsão de sobra
A4: desktop | B4: 109.99 | C4: ok | E4: Vale | F4: 3059.79 | I4: ml | J4: 67.68 | L4: =B19 -> 7956.77 | O4: =L6-L4+L8 -> 2967.18
A5: maisa | B5: 500 | C5: ok | E5: PLR | F5: 3000 | I5: decathlon 3/5 | J5: 106.98 | L5: Entradas
A6: juros obra | B6: 1630 | C6: ok | I6: ml | J6: 50.43 | L6: =F18 -> 10923.95 | O6: Total Poupança
A7: aP | B7: 1277.27 | C7: ok | I7: ml | J7: 15 | L7: Sobrou do mes passado | O7: =L10+L12 -> 0
A8: cartao nu | B8: 3370.1 | C8: ok | I8: amazon 3/7 | J8: 56.78 | L8: =Fevereiro!P4 -> 0
A9: cartao caixa | B9: 950 | C9: ok | I9: ml 4/10 | J9: 34.27 | L9: Colocado na poupança
A10: cartao MP | B10: 0 | C10: ok | I10: netshoes 4/10 | J10: 125.97 | L10: 0
I11: adidas 3/6 | J11: 127.49 | L11: Poupança do mes anterior
I12: cea | J12: 146.64 | L12: 0
I13: decathlon | J13: 111.65
I14: boticario | J14: 99.98
I15: aliexprees 2/4 | J15: 20.03
I16: erica arquiteta 2/3 | J16: 1133.33
I17: dokadosh | J17: 265
E18: total | F18: =SUM(F3:F17) -> 10923.95 | I18: amazon 4/7 | J18: 80.46
A19: total | B19: =SUM(B3:B18) -> 7956.77 | I19: total | J19: =SUM(J3:J18) -> 2468.34
E21: Compras Recorrentes | I21: Cartão MP - parcelamentos | L21: Cartão Caixa - parcelamentos
E22: todo mes é isso | I22: Fevereiro | L22: Fevereiro
I23: Mp Relogio 1/10 | J23: 175.48 | L23: memoria 2/3 | M23: 131.83
I24: ML game 2/10 | J24: 264.59 | L24: memoria 2/4 | M24: 111.79
I25: tenis 2/5 | J25: 111.81 | L25: ml relogio 1/10 | M25: 153.47
I26: tv Vó 2/10 | J26: 142.45 | L26: anuidade | M26: 17.25
I27: relogio | J27: 40.92
E34: Total | F34: =SUM(F23:F27) -> 0
I38: total | J38: =SUM(J23:J37) -> 735.25 | L38: total | M38: =SUM(M23:M37) -> 414.34

Sheet Abril
A1: Contas - saidas | E1: Entradas | I1: Cartão nu - Demonstrativo de parcelamentos
A2: Fevereiro | C2: Status | E2: Fevereiro | G2: Status | I2: Fevereiro | L2: Totais mensal
A3: claro | B3: 119.41 | C3: ok | E3: Salario | F3: 5211.58 | G3: ok | I3: ML PANELAS 1/8 | J3: 189.28 | L3: saidas | O3: previsão de sobra
A4: desktop | B4: 114.9 | C4: ok | E4: Vale | F4: 3000 | I4: ml 2/3 | J4: 96.38 | L4: =B19 -> 10930.43 | O4: =L6-L4+L8+L10 -> -218.85
A5: maisa | B5: 500 | C5: ok | I5: adidas 5/6 | J5: 127.49 | L5: Entradas
A6: juros obra | B6: 1509.36 | C6: ok | I6: ml 2/2 | J6: 87.02 | L6: =F18 -> 8211.58
A7: Ap Intermediaria | B7: 3903.82 | C7: ok | I7: bateria carro | J7: 61.25 | L7: Sobrou do mes passado
A8: cartao nu | B8: 3800 | I8: ml 6/10 | J8: 34.27 | L8: 2500
A9: cartao caixa | B9: 282.94 | I9: tenis 2/2 | J9: 89.99 | L9: Colocado na poupança
A10: cartao bradesco | B10: 0 | C10: ok | I10: puma 3/3 | J10: 120.66 | L10: 0
A11: cartao MP | B11: 700 | C11: ok | I11: aliexpreess 4/4 | J11: 20.03
I12: decathon 5/5 | J12: 106.98
I13: prime anual 2/12 | J13: 13.9
I14: amazon 5/7 | J14: 56.78
I15: amazon 6/7 | J15: 80.46
I16: netshoes 6/10 | J16: 125.97
E18: total | F18: =SUM(F3:F17) -> 8211.58
A19: total | B19: =SUM(B3:B18) -> 10930.43 | I19: total | J19: =SUM(J3:J18) -> 1210.46
E20: Compras Recorrentes
E21: todo mes é isso | I21: Cartão MP - parcelamentos | L21: Cartão Caixa - parcelamentos
E22: apple | I22: Fevereiro | L22: Fevereiro
E23: ml | I23: Mp Relogio 3/10 | J23: 175.48 | L23: memoria 4/4 | M23: 111.79
E24: Gympass | I24: ML game 4/10 | J24: 264.59 | L24: ml relogio 2/10 | M24: 153.47
I25: tenis 4/5 | J25: 111.82 | L25: anuidade | M25: 17.25
I26: tv Vó 4/10 | J26: 142.45
I27: meliMais | J27: 24.9
I28: compra | J28: 30.35
I29: compra | J29: 19.71
E33: Total | F33: =SUM(F22:F26) -> 0
I38: total | J38: =SUM(J23:J37) -> 769.3 | L38: total | M38: =SUM(M23:M37) -> 282.51

Sheet Maio
A1: Contas - saidas | E1: Entradas | H1: Cartão nu - Demonstrativo de parcelamentos
A2: Fevereiro | C2: Status | E2: Fevereiro | H2: Fevereiro | K2: Totais mensal
A3: claro | B3: 119.41 | E3: Salario | F3: 4500 | H3: Ml | I3: 26.65 | K3: saidas | N3: previsão de sobra
A4: desktop | B4: 109.99 | E4: Vale | F4: 3000 | H4: decathlon 4/5 | I4: 106.98 | K4: =B19 -> 3362.85 | N4: =K6-K4+K8+K10 -> 3918.3
A5: maisa | B5: 500 | H5: amazon 4/7 | I5: 56.78 | K5: Entradas
A6: juros obra | B6: 1373 | H6: ml 5/10 | I6: 34.27 | K6: =F18 -> 7500
A7: aP | B7: 1260.45 | H7: netshoes 5/10 | I7: 125.97 | K7: Sobrou do mes passado
A8: cartao nu | B8: 0 | H8: adidas 4/6 | I8: 127.49 | K8: =Abril!O4 -> -218.85
A9: cartao caixa | B9: 0 | H9: aliexprees 3/4 | I9: 20.03 | K9: Colocado na poupança
A10: cartao bradesco | B10: 0 | H10: erica arquiteta | I10: 1133.33 | K10: 0
A11: cartao MP | B11: 0 | H11: amazon 5/7 | I11: 80.46
E18: total | F18: =SUM(F3:F17) -> 7500 | H18: total | I18: =SUM(I3:I17) -> 1711.96
A19: total | B19: =SUM(B3:B18) -> 3362.85
E21: Compras Recorrentes | H21: Cartão MP - parcelamentos | K21: Cartão Caixa - parcelamentos
E22: todo mes é isso | H22: Fevereiro | K22: Fevereiro
H23: Mp Relogio 3/10 | I23: 175.48 | K23: memoria 3/3 | L23: 131.83
H24: ML game 3/10 | I24: 264.59 | K24: memoria 3/4 | L24: 111.79
H25: tenis 3/5 | I25: 111.81 | K25: ml relogio 1/10 | L25: 153.47
H26: tv Vó 3/10 | I26: 142.45 | K26: anuidade | L26: 17.25
H27: relogio | I27: 40.92
E34: Total | F34: =SUM(F23:F27) -> 0
H38: total | I38: =SUM(I23:I37) -> 735.25 | K38: total | L38: =SUM(L23:L37) -> 414.34

Sheet Junho
A1: Contas - saidas | E1: Entradas | H1: compras aleatorias
A2: julho | C2: Status | E2: julho | H2: tipo | I2: valor | K2: Totais mensal
A3: claro | B3: 114.99 | C3: ok | E3: Salario | F3: 4876.92 | H3: pizza barbara | I3: 40.9 | K3: saidas | N3: previsão de sobra
A4: desktop | B4: 119.41 | C4: ok | E4: Vale | F4: 3059.79 | K4: =B19 -> 7170.16 | N4: =K6-K4+K8+K10 -> 5766.55
A5: maisa | B5: 520 | C5: ok | E5: decimo terceiro | F5: 5000 | K5: Entradas
A6: juros obra | B6: 1700 | C6: ok | K6: =F18 -> 12936.71
A7: cartao nu | B7: 3000 | K7: Sobrou do mes passado
A8: cartao caixa | B8: 877.52 | K8: 0
A9: cartao bradesco | B9: 0 | K9: Colocado na poupança
A10: cartao MP | B10: 838.24 | C10: ok | K10: 0
E18: total | F18: =SUM(F3:F17) -> 12936.71 | H18: total | I18: =SUM(I3:I17) -> 40.9
A19: total | B19: =SUM(B3:B18) -> 7170.16

Sheet Julho
A1: Contas - saidas | E1: Entradas | I1: Cartão nu - Demonstrativo de parcelamentos
A2: Julho | C2: Status | E2: Julho | I2: Julho | L2: Totais mensal
A3: claro | B3: 119.41 | E3: Salario | F3: 4500 | L3: saidas | O3: previsão de sobra
A4: desktop | B4: 109.99 | E4: Vale | F4: 3000 | L4: =B19 -> 3362.85 | O4: =L6-L4+L8+L10 -> 9903.7
A5: maisa | B5: 500 | L5: Entradas
A6: juros obra | B6: 1373 | L6: =F18 -> 7500
A7: aP | B7: 1260.45 | L7: Sobrou do mes passado
A8: cartao nu | L8: =Junho!N4 -> 5766.55
L9: Colocado na poupança
L10: 0
E18: total | F18: =SUM(F3:F17) -> 7500 | I18: total | J18: =SUM(J3:J17) -> 0
A19: total | B19: =SUM(B3:B18) -> 3362.85
E21: Compras Recorrentes
E22: todo mes é isso
E34: Total | F34: =SUM(F23:F27) -> 0

Sheet Agosto
A1: Contas - saidas | E1: Entradas | H1: Compras parceladas
A2: Agosto | C2: Status | E2: Agosto | H2: Agosto | M2: Totais mensal
A3: claro | B3: 119.41 | C3: ok | E3: Salario | F3: 4876.92 | H3: Compra | I3: valor | J3: Parcelas | K3: Instituição | M3: saidas | P3: previsão de sobra
A4: desktop | B4: 114.99 | C4: ok | E4: Vale | F4: 3059.79 | H4: Tv Casas Bahia | I4: 142.4 | J4: 07-10 | K4: ML | M4: =B19 -> 9772.93 | P4: =M6-M4+M8+M10 -> 10212.66
A5: maisa | B5: 500 | C5: ok | E5: ferias | F5: 12048.88 | H5: Retroid | I5: 264.52 | J5: 07-10 | K5: ML | M5: Entradas
A6: aP | B6: 1500 | C6: ok | H6: Relogio | I6: 175.44 | J6: 06-10 | K6: ML | M6: =F18 -> 19985.59
A7: cartao nu | B7: 1958.02 | C7: ok | H7: Relogio | I7: 137.99 | J7: 06-10 | K7: ML | M7: Sobrou do mes passado
A8: cartao caixa | B8: 384.91 | C8: ok | H8: Mouse | I8: 61.09 | J8: 01-10 | K8: ML | M8: 0
A9: mercado pago | B9: 806.34 | C9: ok | H9: Tinta Ap | I9: 115 | J9: 01-04 | K9: Loja | M9: Colocado na poupança
A10: bradesco | B10: 54.8 | C10: ok | H10: Material Ap | I10: 645.33 | J10: 01-10 | K10: Loja | M10: 0
A11: Condominio | B11: 394.82 | C11: ok
A12: Cartão nu 2 | B12: 1009 | C12: ok
A13: pedreiro | B13: 2831 | C13: Ok
A14: claro proporcinal | B14: 99.64 | C14: ok
E18: total | F18: =SUM(F3:F17) -> 19985.59 | H18: total | I18: =SUM(I3:I17) -> 1541.77
A19: total | B19: =SUM(B3:B18) -> 9772.93
E21: Compras Recorrentes
E22: todo mes é isso
E23: Meli Plus | F23: 24.9
E24: Amazon anuncios | F24: 10
E25: paramount | F25: 13.95
E26: WellHub | F26: 139.9
E27: Apple | F27: 59.9
E34: Total | F34: =SUM(F23:F33) -> 248.65

Sheet Setembro
A1: Contas - saidas | E1: Entradas | I1: Compras parceladas
A2: Setembro | C2: Status | E2: Setembro | I2: Setembro | N2: Totais mensal
A3: claro | B3: 36.59 | C3: Ok | E3: Salario | F3: 3204.18 | I3: Compra | J3: valor | K3: Parcelas | L3: Instituição | N3: saidas | Q3: previsão de sobra
A4: desktop | B4: 114.99 | C4: Ok | E4: Vale | F4: 3000 | I4: Material Ap | J4: 645.33 | K4: 02-10 | L4: NU | N4: =B19 -> 5751.23 | Q4: 5000
A5: maisa | B5: 500 | C5: Ok | I5: NKR TINTAS | J5: 115 | K5: 02-04 | L5: NU | N5: Entradas
A6: aP | B6: 1500 | C6: Ok | I6: Sacada | J6: 572 | K6: - | L6: Bradesco | N6: =F18 -> 6204.18
A7: cartao nu | B7: 1794.65 | C7: Ok | I7: Retroid | J7: 264.52 | K7: 08-10 | L7: ML | N7: Sobrou do mes passado
A8: cartao caixa | B8: 17 | C8: Ok | I8: Tv Casas Bahia | J8: 142.4 | K8: 08-10 | L8: ML | N8: =Agosto!P4 -> 10212.66
A9: mercado pago | B9: 1340 | C9: Ok | I9: Relogio | J9: 175.44 | K9: 07-10 | L9: ML | N9: Colocado na poupança
A10: bradesco | B10: 0 | C10: Ok | I10: Relogio | J10: 137.99 | K10: 07-10 | L10: ML | N10: 0
A11: Condominio | B11: 400 | C11: Ok | I11: Mouse | J11: 61 | K11: 02-10 | L11: ML
A12: CPFL | B12: 48 | C12: Ok | I12: marmore | J12: 119 | K12: 45690 | L12: ML
A13: pedreiro | B13: 0 | I13: furadeira | J13: 24.87 | K13: 45870 | L13: ML
I14: torneira | J14: 62.49 | K14: 45717 | L14: ML
I15: kit banheiro | J15: 55.42 | K15: 45839 | L15: ML
I16: Luzes | J16: 79.92 | K16: 45931 | L16: ML
I17: ap | J17: 52.38 | K17: 45778 | L17: ML
E18: total | F18: =SUM(F3:F17) -> 6204.18 | I18: Luz cozinha | J18: 71.8 | K18: 01-05 | L18: ML
A19: total | B19: =SUM(B3:B18) -> 5751.23 | I19: ferramentas | J19: 72.91 | K19: 01-10 | L19: ML
I20: luz sala | J20: 64.8 | K20: 01-05 | L20: ML
E21: Compras Recorrentes | I21: coisas AP | J21: 73.31 | K21: 01-05 | L21: ML
E22: todo mes é isso
E23: Meli Plus | F23: 24.9
E24: Amazon anuncios | F24: 10 | I24: total | J24: =SUM(J4:J23) -> 2790.58
E25: WellHub | F25: 139.9
E26: Apple | F26: 59.9
E34: Total | F34: =SUM(F23:F33) -> 234.7

Sheet Outubro
A1: Contas - saidas | E1: Entradas | I1: Compras parceladas
A2: Outubro | C2: Status | E2: Outubro | I2: Outubro | N2: Totais mensal
A3: claro | B3: 119.9 | C3: Ok | E3: Salario | F3: 1441.54 | G3: Ok | I3: Compra | J3: valor | K3: Parcelas | L3: Instituição | N3: saidas | Q3: previsão de sobra
A4: desktop | B4: 114.99 | C4: Ok | E4: Vale | F4: 3651.96 | G4: OK | I4: Material Ap | J4: 645.33 | K4: 03-10 | L4: NU | N4: =B19 -> 7581.89 | Q4: 3700
A5: maisa | B5: 500 | C5: Ok | E5: Entrada game | F5: 2000 | G5: Ok | I5: NKR TINTAS | J5: 115 | K5: 03-04 | L5: NU | N5: Entradas
A6: aP | B6: 1400 | C6: Ok | I6: Sacada | J6: 572 | K6: 01-10 | L6: Bradesco | N6: =F18 -> 7093.5
A7: cartao nu | B7: 2530 | C7: Ok | I7: Retroid | J7: 264.52 | K7: 09-10 | L7: ML | N7: Sobrou do mes passado
A8: cartao caixa | B8: 17 | C8: Ok | I8: Tv Casas Bahia | J8: 142.4 | K8: 09-10 | L8: ML | N8: 0
A9: mercado pago | B9: 1500 | C9: Ok | I9: Relogio | J9: 175.44 | K9: 08-10 | L9: ML | N9: Colocado na poupança
A10: bradesco | B10: 572 | C10: Ok | I10: Relogio | J10: 137.99 | K10: 08-10 | L10: ML | N10: 0
A11: Condominio | B11: 442 | C11: Ok | I11: Mouse | J11: 61 | K11: 02-10 | L11: ML
A12: CPFL | B12: 46 | C12: OK | I12: furadeira | J12: 24.87 | K12: 02-08 | L12: ML
A13: Argamassa | B13: 340 | C13: Ok | I13: torneira | J13: 62.49 | K13: 02-03 | L13: ML
I14: kit banheiro | J14: 55.42 | K14: 02-07 | L14: ML
I15: Luzes | J15: 79.92 | K15: 02-10 | L15: ML
I16: ap | J16: 52.38 | K16: 02-05 | L16: ML
I17: Luz cozinha | J17: 71.8 | K17: 02-05 | L17: ML
E18: total | F18: =SUM(F3:F17) -> 7093.5 | I18: ferramentas | J18: 72.91 | K18: 02-10 | L18: ML
A19: total | B19: =SUM(B3:B18) -> 7581.89 | I19: luz sala | J19: 64.8 | K19: 02-05 | L19: ML
I20: coisas AP | J20: 73.31 | K20: 02-05 | L20: ML
E21: Compras Recorrentes
E22: todo mes é isso
E23: Meli Plus | F23: 24.9
E24: Amazon anuncios | F24: 10 | I24: total | J24: =SUM(J4:J23) -> 2671.58
E25: WellHub | F25: 139.9
E26: Apple | F26: 59.9
E34: Total | F34: =SUM(F23:F33) -> 234.7

Sheet Novembro
A1: Contas - saidas | E1: Entradas | I1: Compras parceladas
A2: Novembro | C2: Status | E2: Novembro | I2: Novembro | N2: Totais mensal
A3: claro | B3: 119.9 | C3: ok | E3: Salario | F3: 4876.92 | I3: Compra | J3: valor | K3: Parcelas | L3: Instituição | N3: saidas | Q3: previsão de sobra
A4: desktop | B4: 5 | C4: ok | E4: Vale | F4: 3059.79 | I4: Material Ap | J4: 645.33 | K4: 04-10 | L4: NU | N4: =B19 -> 11550.75 | Q4: =N6-N4+N8+N10 -> 85.96
A5: maisa | B5: 500 | C5: ok | I5: NKR TINTAS | J5: 115 | K5: 04-04 | L5: NU | N5: Entradas
A6: aP | B6: 1480 | C6: ok | I6: Sacada | J6: 572 | K6: 02-10 | L6: Bradesco | N6: =F18 -> 7936.71
A7: cartao nu | B7: 2550 | C7: Ok | I7: Retroid | J7: 264.52 | K7: 10-10 | L7: ML | N7: Sobrou do mes passado
A8: mercado pago | B8: 2869.66 | C8: ok | I8: Tv Casas Bahia | J8: 142.4 | K8: 10-10 | L8: ML | N8: =Outubro!Q4 -> 3700
A9: bradesco | B9: 572 | C9: ok | I9: Relogio | J9: 175.44 | K9: 09-10 | L9: ML | N9: Colocado na poupança
A10: Condominio | B10: 464.21 | C10: ok | I10: Relogio | J10: 137.99 | K10: 09-10 | L10: ML | N10: 0
A11: CPFL | B11: 48.98 | C11: ok | I11: Mouse | J11: 61 | K11: 03-10 | L11: ML
A12: Pedreiro | B12: 750 | C12: ok | I12: furadeira | J12: 24.87 | K12: 03-08 | L12: ML
A13: pedreiro | B13: 791 | C13: ok | I13: torneira | J13: 62.49 | K13: 03-03 | L13: ML
A14: pedreiro | B14: 150 | C14: ok | I14: kit banheiro | J14: 55.42 | K14: 03-07 | L14: ML
A15: pedreiro | B15: 500 | C15: ok | I15: Luzes | J15: 79.92 | K15: 03-10 | L15: ML
A16: pedreiro | B16: 750 | C16: ok | I16: ap | J16: 52.38 | K16: 03-05 | L16: ML
I17: Luz cozinha | J17: 71.8 | K17: 03-05 | L17: ML
E18: total | F18: =SUM(F3:F17) -> 7936.71 | I18: ferramentas | J18: 72.91 | K18: 03-10 | L18: ML
A19: total | B19: =SUM(B3:B18) -> 11550.75 | I19: luz sala | J19: 64.8 | K19: 03-05 | L19: ML
I20: coisas AP | J20: 73.31 | K20: 03-05 | L20: ML
E21: Compras Recorrentes | I21: decathon | J21: 77.49 | K21: 04-05 | L21: NU
E22: todo mes é isso
E23: Meli Plus | F23: 24.9
E24: Amazon anuncios | F24: 10 | I24: total | J24: =SUM(J4:J23) -> 2749.07
E25: WellHub | F25: 139.9
E26: Apple | F26: 59.9
E34: Total | F34: =SUM(F23:F33) -> 234.7

Sheet Dezembro
A1: Contas - saidas | E1: Entradas | I1: Compras parceladas
A2: Dezembro | C2: Status | E2: Dezembro | I2: Dezembro | N2: Totais mensal
A3: cartao nu | B3: 3128.68 | C3: ok | E3: Salario | F3: 4876.92 | G3: ok | I3: Compra | J3: valor | K3: Parcelas | L3: Instituição | N3: saidas | Q3: previsão de sobra
A4: mercado pago | B4: 2272 | C4: ok | E4: Vale | F4: 3059.79 | G4: ok | I4: Material Ap | J4: 645.33 | K4: 05-10 | L4: NU | N4: =B19 -> 9616.75 | Q4: 0
A5: bradesco | B5: 572 | C5: ok | E5: decimo | F5: 2653.95 | G5: ok | I5: Sacada | J5: 572 | K5: 03-10 | L5: Bradesco | N5: Entradas
A6: maisa | B6: 500 | C6: ok | I6: Relogio | J6: 175.44 | K6: 10-10 | L6: ML | N6: =F18 -> 10590.66
A7: aP | B7: 1500 | C7: ok | I7: Relogio | J7: 137.99 | K7: 10-10 | L7: ML | N7: Sobrou do mes passado
A8: claro | B8: 159.79 | C8: ok | I8: Mouse | J8: 61 | K8: 04-10 | L8: ML | N8: 135
A9: Condominio | B9: 461.62 | C9: ok | I9: furadeira | J9: 24.87 | K9: 04-08 | L9: ML | N9: Colocado na poupança
A10: CPFL | B10: 44.67 | C10: ok | I10: kit banheiro | J10: 55.42 | K10: 04-07 | L10: ML | N10: 0
A11: emprestimo | B11: 537.99 | C11: ok | I11: Luzes | J11: 79.92 | K11: 04-10 | L11: ML
A12: figurino | B12: 440 | C12: ok | I12: ap | J12: 52.38 | K12: 04-05 | L12: ML
I13: Luz cozinha | J13: 71.8 | K13: 04-05 | L13: ML
I14: ferramentas | J14: 72.91 | K14: 10-10 | L14: ML
I15: luz sala | J15: 64.8 | K15: 04-05 | L15: ML
I16: coisas AP | J16: 73.31 | K16: 04-05 | L16: ML
I17: decathon | J17: 77.49 | K17: 05-05 | L17: NU
E18: total | F18: =SUM(F3:F17) -> 10590.66 | I18: 2PRO | J18: 21.27 | K18: 03-04 | L18: ML
A19: total | B19: =SUM(B3:B18) -> 9616.75 | I19: Privada | J19: 153 | K19: 03-08 | L19: ML
I20: Infra AR | J20: 258.57 | K20: 02-10 | L20: ML
E21: Compras Recorrentes | I21: Roupa Italiana | J21: 93.32 | K21: 02-03 | L21: ML
E22: todo mes é isso
E23: Meli Plus | F23: 24.9
E24: Amazon anuncios | F24: 10 | I24: total | J24: =SUM(J4:J23) -> 2690.82
E25: WellHub | F25: 139.9
E26: Apple | F26: 59.9
E34: Total | F34: =SUM(F23:F33) -> 234.7

Sheet Janeiro26
A1: Contas - saidas | E1: Entradas | I1: Compras parceladas
A2: Janeiro | C2: Status | E2: Janeiro | I2: Janeiro | N2: Totais mensal
A3: cartao nu | B3: 2645.54 | C3: ok | E3: Salario | F3: 6000 | G3: ok | I3: Compra | J3: valor | K3: Parcelas | L3: Instituição | N3: saidas | Q3: previsão de sobra
A4: mercado pago | B4: 2384.59 | C4: ok | E4: Vale | F4: 3059.79 | G4: ok | I4: Material Ap | J4: 645.33 | K4: 06-10 | L4: NU | N4: =B19 -> 8887.92 | Q4: 0
A5: bradesco | B5: 572 | C5: ok | I5: celular joao | J5: 69.25 | K5: 02-12 | L5: NU | N5: Entradas
A6: maisa | B6: 500 | C6: ok | I6: panela mae | J6: 31.8 | K6: 02-05 | L6: NU | N6: =F18 -> 9059.79
A7: aP | B7: 1500 | C7: ok | I7: acabamentos AP | J7: 177.73 | K7: 02-03 | L7: NU | N7: Sobrou do mes passado
A8: claro | B8: 159.79 | C8: ok | I8: Sacada | J8: 572 | K8: 04-10 | L8: Bradesco | N8: =Dezembro!Q4 -> 0
A9: Condominio | B9: 576 | C9: ok | I9: pisos | J9: 107.91 | K9: 02-08 | L9: ML | N9: Colocado na poupança
A10: emprestimo | B10: 550 | C10: ok | I10: Roupa italiana | J10: 93.32 | K10: 03-03 | L10: ML | N10: 0
I11: Mouse | J11: 61 | K11: 05-10 | L11: ML
I12: furadeira | J12: 24.87 | K12: 05-08 | L12: ML
I13: kit banheiro | J13: 55.42 | K13: 05-07 | L13: ML
I14: Luzes | J14: 79.92 | K14: 05-10 | L14: ML
I15: ap | J15: 52.38 | K15: 05-05 | L15: ML
I16: Luz cozinha | J16: 71.8 | K16: 05-05 | L16: ML
I17: luz sala | J17: 64.8 | K17: 05-05 | L17: ML
E18: total | F18: =SUM(F3:F17) -> 9059.79 | I18: coisas AP | J18: 73.31 | K18: 05-05 | L18: ML
A19: total | B19: =SUM(B3:B18) -> 8887.92 | I19: 2PRO | J19: 21.27 | K19: 04-04 | L19: ML
I20: Privada | J20: 153 | K20: 04-08 | L20: ML
E21: Compras Recorrentes | I21: Infra AR | J21: 258.57 | K21: 03-10 | L21: ML
E22: todo mes é isso | I22: nao sei | J22: 66.66 | K22: 02-06 | L22: ML
E23: Meli Plus | F23: 24.9 | I23: Pisos | J23: 92.26 | K23: 02-02 | L23: ML
E24: Amazon anuncios | F24: 10 | I24: camisa palmeiras | J24: 83.33 | K24: 02-06 | L24: ML
E25: WellHub | F25: 139.9 | I25: ? | J25: 72.91 | K25: 05-10 | L25: ML
E26: Apple | F26: 59.9
I27: total | J27: =SUM(J4:J26) -> 2928.84
E34: Total | F34: =SUM(F23:F33) -> 234.7

Sheet Fevereiro26
A1: Contas - saidas | E1: Entradas | I1: Compras parceladas
A2: Fevereiro | C2: Status | E2: Fevereiro | I2: Fevereiro | N2: Totais mensal
A3: cartao nu | B3: 2600 | C3: ok | E3: Salario | F3: 4984.54 | G3: ok | I3: Compra | J3: valor | K3: Parcelas | L3: Instituição | N3: saidas | Q3: previsão de sobra
A4: mercado pago | B4: 1500 | C4: ok | E4: Vale | F4: 3059.79 | G4: ok | I4: Material Ap | J4: 645.33 | K4: 07-10 | L4: NU | N4: =B19 -> 7935.83 | Q4: =N6-N4+N8+N10 -> 108.5
A5: bradesco | B5: 572 | C5: ok | I5: dafiti | J5: 61.1 | K5: 02-04 | L5: NU | N5: Entradas
A6: maisa | B6: 500 | C6: ok | I6: ? | J6: 69.25 | K6: 03-12 | L6: NU | N6: =F18 -> 8044.33
A7: aP | B7: 1490 | C7: ok | I7: ML | J7: 31.8 | K7: 03-05 | L7: NU | N7: Sobrou do mes passado
A8: claro | B8: 159.79 | C8: ok | I8: centauro | J8: 90.98 | K8: 02-04 | L8: NU | N8: =Janeiro26!Q4 -> 0
A9: Condominio | B9: 527.57 | C9: ok | I9: ML | J9: 177.73 | K9: 03-03 | L9: NU | N9: Colocado na poupança
A10: CPFL | B10: 43.38 | C10: ok | I10: PSN | J10: 37.52 | K10: 02-02 | L10: NU | N10: 0
A11: emprestimo | B11: 543.09 | C11: ok | I11: Steam | J11: 20.09 | K11: 02-02 | L11: NU
I12: Sacada | J12: 572 | K12: 05-10 | L12: Bradesco
I13: Mouse | J13: 61 | K13: 07-10 | L13: ML
I14: furadeira | J14: 24.87 | K14: 06-08 | L14: ML
I15: kit banheiro | J15: 55.42 | K15: 06-07 | L15: ML
I16: Luzes | J16: 79.92 | K16: 06-10 | L16: ML
I17: ? | J17: 72.91 | K17: 06-10 | L17: ML
E18: total | F18: =SUM(F3:F17) -> 8044.33 | I18: privada | J18: 153 | K18: 05-08 | L18: ML
A19: total | B19: =SUM(B3:B18) -> 7935.83 | I19: Infra AR | J19: 258.57 | K19: 04-10 | L19: ML
I20: Horto pisos | J20: 107.91 | K20: 03-08 | L20: ML
E21: Compras Recorrentes | I21: ssd note | J21: 66.66 | K21: 03-06 | L21: ML
E22: todo mes é isso | I22: ? | J22: 83.33 | K22: 03-06 | L22: ML
E23: Meli Plus | F23: 24.9 | I23: ? | J23: 42.15 | K23: 02-08 | L23: ML
E24: Amazon anuncios | F24: 10 | I24: ? | J24: 79.05 | K24: 02-03 | L24: ML
E25: WellHub | F25: 139.9 | I25: Controle pc | J25: 91.81 | K25: 02-05 | L25: ML
E26: Apple | F26: 59.9 | I26: ? | J26: 61.3 | K26: 02-04 | L26: ML
I27: Controle pc | J27: 69.85 | K27: 02-07 | L27: ML
I28: roçadeira | J28: 240.58 | K28: 02-03 | L28: ML
I29: WYD | J29: 133.34 | K29: 01-03 | L29: ML
I33: total | J33: =SUM(J4:J32) -> 3387.47
E34: Total | F34: =SUM(F23:F33) -> 234.7

Sheet Março26
A1: Contas - saidas | E1: Entradas | I1: Compras parceladas
A2: Março | C2: Status | E2: Março | I2: Março | N2: Totais mensal
A3: cartao nu | B3: 0 | C3: ok | E3: Salario | F3: 5437.09 | G3: ok | I3: Compra | J3: valor | K3: Parcelas | L3: Instituição | N3: saidas | Q3: previsão de sobra
A4: mercado pago | B4: 900 | C4: ok | E4: Vale | F4: 3136.84 | G4: ok | I4: Material Ap | J4: 645.33 | K4: 08-10 | L4: NU | N4: =B19 -> 8186.73 | Q4: 0
A5: bradesco | B5: 1572 | C5: ok | I5: dafiti(presente B) | J5: 61.1 | K5: 03-04 | L5: NU | N5: Entradas
A6: maisa | B6: 500 | C6: ok | I6: ? | J6: 69.25 | K6: 04-12 | L6: NU | N6: =F18 -> 8573.93
A7: aP | B7: 1500 | C7: ok | I7: ML | J7: 31.8 | K7: 04-05 | L7: NU | N7: Sobrou do mes passado
A8: claro | B8: 159.79 | C8: ok | I8: centauro | J8: 90.98 | K8: 03-04 | L8: NU | N8: =Fevereiro26!Q4 -> 108.5
A9: Condominio | B9: 517.95 | C9: ok | I9: Sacada | J9: 572 | K9: 06-10 | L9: Bradesco | N9: Colocado na poupança
A10: CPFL | B10: 42.78 | C10: ok | I10: Mouse | J10: 61 | K10: 08-10 | L10: ML | N10: 0
A11: emprestimo | B11: 543.09 | C11: ok | I11: furadeira | J11: 24.87 | K11: 07-08 | L11: ML
A12: iptu | B12: 110.71 | C12: ok | I12: kit banheiro | J12: 55.42 | K12: 07-07 | L12: ML
A13: mercado pago | B13: 2340.41 | C13: ok | I13: Luzes | J13: 79.92 | K13: 07-10 | L13: ML
I14: ? | J14: 72.91 | K14: 07-10 | L14: ML
I15: privada | J15: 153 | K15: 06-08 | L15: ML
I16: Infra AR | J16: 258.57 | K16: 05-10 | L16: ML
I17: Horto pisos | J17: 107.91 | K17: 04-08 | L17: ML
E18: total | F18: =SUM(F3:F17) -> 8573.93 | I18: ssd note | J18: 66.66 | K18: 04-06 | L18: ML
A19: total | B19: =SUM(B3:B18) -> 8186.73 | I19: ? | J19: 83.33 | K19: 04-06 | L19: ML
I20: ? | J20: 42.15 | K20: 03-08 | L20: ML
E21: Compras Recorrentes | I21: ? | J21: 79.05 | K21: 03-03 | L21: ML
E22: todo mes é isso | I22: Controle pc | J22: 91.81 | K22: 04-05 | L22: ML
E23: Meli Plus | F23: 24.9 | I23: ? | J23: 61.3 | K23: 03-04 | L23: ML
E24: Amazon anuncios | F24: 10 | I24: Controle pc | J24: 69.85 | K24: 03-07 | L24: ML
E25: WellHub | F25: 139.9 | I25: roçadeira | J25: 240.58 | K25: 03-03 | L25: ML
E26: Apple | F26: 59.9 | I26: WYD | J26: 133.34 | K26: 02-03 | L26: ML
I33: total | J33: =SUM(J4:J32) -> 3152.13
E34: Total | F34: =SUM(F23:F33) -> 234.7

Sheet Abril26
A1: Contas - saidas | E1: Entradas | I1: Compras parceladas
A2: Janeiro | C2: Status | E2: Janeiro | I2: Janeiro | N2: Totais mensal
A3: cartao nu(atrasado) | B3: 3566.11 | C3: ok | E3: Salario | F3: 5133.97 | G3: ok | I3: Compra | J3: valor | K3: Parcelas | L3: Instituição | N3: saidas | Q3: previsão de sobra
A4: cartao nu | B4: 2500 | C4: ok | E4: Vale | F4: 3136.84 | G4: ok | I4: Material Ap | J4: 645.33 | K4: 09-10 | L4: NU | N4: =B19 -> 12258.37 | Q4: 0
A5: mercado pago | B5: 1200 | C5: ok | E5: PLR | F5: 4177.63 | G5: ok | I5: dafiti(presente B) | J5: 61.1 | K5: 04-04 | L5: NU | N5: Entradas
A6: bradesco | B6: 1572 | C6: ok | I6: ? | J6: 69.25 | K6: 05-12 | L6: NU | N6: =F18 -> 12448.44
A7: maisa | B7: 500 | C7: ok | I7: ML | J7: 31.8 | K7: 05-05 | L7: NU | N7: Sobrou do mes passado
A8: aP | B8: 1511 | C8: ok | I8: centauro | J8: 90.98 | K8: 04-04 | L8: NU | N8: ='Março26'!Q4 -> 0
A9: claro | B9: 159.79 | C9: ok | I9: Sacada | J9: 572 | K9: 07-10 | L9: Bradesco | N9: Colocado na poupança
A10: Condominio | B10: 554.93 | C10: ok | I10: Mouse | J10: 61 | K10: 09-10 | L10: ML | N10: 0
A11: CPFL | B11: 42.64 | C11: ok | I11: furadeira | J11: 24.87 | K11: 08-08 | L11: ML
A12: emprestimo | B12: 541.19 | C12: ok | I12: Luzes | J12: 79.92 | K12: 08-10 | L12: ML
A13: iptu | B13: 110.71 | C13: ok | I13: ? | J13: 72.91 | K13: 08-10 | L13: ML
I14: privada | J14: 153 | K14: 07-08 | L14: ML
I15: Infra AR | J15: 258.57 | K15: 06-10 | L15: ML
I16: Horto pisos | J16: 107.91 | K16: 05-08 | L16: ML
I17: ssd note | J17: 66.66 | K17: 05-06 | L17: ML
E18: total | F18: =SUM(F3:F17) -> 12448.44 | I18: ? | J18: 83.33 | K18: 05-06 | L18: ML
A19: total | B19: =SUM(B3:B18) -> 12258.37 | I19: ? | J19: 42.15 | K19: 04-08 | L19: ML
I20: Controle pc | J20: 91.81 | K20: 05-05 | L20: ML
E21: Compras Recorrentes | I21: ? | J21: 61.3 | K21: 04-04 | L21: ML
E22: todo mes é isso | I22: Controle pc | J22: 69.85 | K22: 04-07 | L22: ML
E23: Meli Plus | F23: 10 | I23: WYD | J23: 133.34 | K23: 03-03 | L23: ML
E24: WellHub | F24: 149.9
E25: Apple | F25: 59.9
I33: total | J33: =SUM(J4:J32) -> 2777.08
E34: Total | F34: =SUM(F23:F33) -> 219.8

Sheet Maio26
A1: Contas - saidas | E1: Entradas | I1: Compras parceladas
A2: Janeiro | C2: Status | E2: Janeiro | I2: Janeiro | N2: Totais mensal
A3: cartao nu | B3: 3400 | C3: ok | E3: Salario | F3: 5133.97 | I3: Compra | J3: valor | K3: Parcelas | L3: Instituição | N3: saidas | Q3: previsão de sobra
A4: mercado pago | B4: 1918 | C4: ok | E4: Vale | F4: 0 | I4: Prime | J4: 16.68 | K4: 02/10 | L4: NU | N4: =B19 -> 19978.46 | Q4: 0
A5: bradesco | B5: 1572 | C5: ok | E5: ferias | F5: 12000 | I5: drogal | J5: 280.24 | K5: 03/03 | L5: NU | N5: Entradas
A6: maisa | B6: 500 | C6: ok | I6: Hortopisos | J6: 645.33 | K6: 10/10 | L6: NU | N6: =F18 -> 17133.97
A7: aP | B7: 1500 | C7: ok | I7: ML | J7: 69.25 | K7: 6/12 | L7: NU | N7: Sobrou do mes passado
A8: claro | B8: 159.79 | C8: ok | I8: Growth | J8: 44.86 | K8: 03/04 | L8: NU | N8: =Abril26!Q4 -> 0
A9: Condominio | B9: 520 | C9: Ok | I9: Play | J9: 37.47 | K9: 02/02 | L9: NU | N9: Colocado na poupança
A10: CPFL | B10: 43.03 | C10: ok | I10: parcelamento fatura | J10: 218 | K10: 01/03 | L10: NU | N10: 0
A11: emprestimo | B11: 539.29 | C11: ok | I11: pedras | J11: 783.34 | K11: 01/03 | L11: Bradesco
A12: iptu | B12: 110.71 | C12: ok | I12: Infra Ar | J12: 572 | K12: 09/10 | L12: Bradesco
A13: emprestimo final | B13: 715.64 | C13: ok | I13: gesso | J13: 1000 | K13: 04/05 | L13: Bradesco
A14: pedras | B14: 9000 | C14: ok
E18: total | F18: =SUM(F3:F17) -> 17133.97
A19: total | B19: =SUM(B3:B18) -> 19978.46
E21: Compras Recorrentes
E22: todo mes é isso
E23: Meli Plus | F23: 10
E24: WellHub | F24: 149.9
E25: Apple | F25: 59.9
E26: Prime sem anuncios | F26: 10
E27: Prime | F27: 16.68
I33: total | J33: =SUM(J4:J32) -> 3667.17
E34: Total | F34: =SUM(F23:F33) -> 246.48

Sheet Junho26
A1: Contas - saidas | E1: Entradas | I1: Compras parceladas
A2: Janeiro | C2: Status | E2: Janeiro | I2: Janeiro | N2: Totais mensal
A3: cartao nu | B3: 2400 | C3: x | E3: Salario | F3: 3400 | I3: Compra | J3: valor | K3: Parcelas | L3: Instituição | N3: saidas | Q3: previsão de sobra
A4: mercado pago | B4: 2533.98 | C4: ok | E4: Vale | F4: 3050 | I4: pedras | J4: 783.34 | K4: 01/03 | L4: Bradesco | N4: =B19 -> 13095.65 | Q4: 0
A5: bradesco | B5: 3550.53 | C5: ok | I5: Infra Ar | J5: 572 | K5: 09/10 | L5: Bradesco | N5: Entradas
A6: maisa | B6: 500 | C6: ok | I6: gesso | J6: 1000 | K6: 04/05 | L6: Bradesco | N6: =F18 -> 6450
A7: aP | B7: 2730 | C7: ok | I7: Prime | J7: 16.68 | K7: 03/10 | L7: NU | N7: Sobrou do mes passado
A8: claro | B8: 159.79 | C8: ok | I8: Growth | J8: 44.86 | K8: 04/04 | L8: NU | N8: =Maio26!Q4 -> 0
A9: Condominio | B9: 521.82 | C9: ok | I9: ML | J9: 69.25 | K9: 07/12 | L9: NU | N9: Colocado na poupança
A10: CPFL | B10: 45.73 | C10: ok | I10: Parcelamento | J10: 218.48 | K10: 02/03 | L10: NU | N10: 0
A11: note | B11: 543.09 | C11: ok | I11: ? | J11: 79.92 | K11: 10/10 | L11: ML
A12: iptu | B12: 110.71 | C12: ok | I12: ? | J12: 72.91 | K12: 10/10 | L12: ML
I13: infra Ar | J13: 258.57 | K13: 08/10 | L13: ML
I14: Pisos | J14: 107.91 | K14: 07/08 | L14: ML
I15: ? | J15: 42.15 | K15: 06/08 | L15: ML
I16: ? | J16: 69.85 | K16: 06/07 | L16: ML
I17: Puma | J17: 100.19 | K17: 03/10 | L17: ML
E18: total | F18: =SUM(F3:F17) -> 6450 | I18: trans | J18: 104.17 | K18: 02/02 | L18: ML
A19: total | B19: =SUM(B3:B18) -> 13095.65 | I19: Riot | J19: 63.3 | K19: 02/03 | L19: ML
I20: ? | J20: 138.33 | K20: 02/06 | L20: ML
E21: Compras Recorrentes | I21: ? | J21: 111.2 | K21: 02/10 | L21: ML
E22: todo mes é isso | I22: ? | J22: 146.27 | K22: 02/06 | L22: ML
E23: Meli Plus | F23: 10 | I23: total | J23: =SUM(J4:J22) -> 3999.38
E24: WellHub | F24: 149.9
E25: Apple | F25: 59.9
E26: Prime sem anuncios | F26: 10
E27: Prime | F27: 16.68
E34: Total | F34: =SUM(F23:F33) -> 246.48

Sheet Julho26
A1: Contas - saidas | E1: Entradas | I1: Compras parceladas
A2: Julho | C2: Status | E2: Julho | I2: Julho | N2: Totais mensal
A3: cartao nu | B3: 3500 | E3: Salario | F3: 5384.32 | I3: Compra | J3: valor | K3: Parcelas | L3: Instituição | N3: saidas | Q3: previsão de sobra
A4: mercado pago | B4: 1200 | E4: Vale | F4: 3050 | I4: pedras | J4: 783.34 | K4: 02/03 | L4: Bradesco | N4: =B19 -> 14141.03 | Q4: 0
A5: bradesco | B5: 3550.53 | E5: Decimo parcela 1 | F5: 5487 | I5: Infra Ar | J5: 572 | K5: 10/10 | L5: Bradesco | N5: Entradas
A6: maisa | B6: 500 | I6: gesso | J6: 1000 | K6: 05/05 | L6: Bradesco | N6: =F18 -> 13921.32
A7: aP | B7: 1500 | I7: carro | J7: 711.2 | K7: 02/06 | L7: bradesco | N7: Sobrou do mes passado
A8: claro | B8: 159.79 | I8: celular | J8: 483.89 | K8: 02/21 | L8: bradesco | N8: =Junho26!Q4 -> 0
A9: Condominio | B9: 530 | I9: Parcelamento | J9: 218.48 | K9: 03/03 | L9: NU | N9: Colocado na poupança
A10: CPFL | B10: 40 | I10: ML | J10: 69.25 | K10: 08/12 | L10: NU | N10: 0
A11: emprestimo | B11: 550 | I11: Prime | J11: 16.68 | K11: 04/10 | L11: NU
A12: iptu | B12: 110.71 | I12: Dompas | J12: 118.66 | K12: 02/03 | L12: NU
A13: limite caixa | B13: 2500 | I13: DrogaSil | J13: 452.45 | K13: 02/02 | L13: NU
I14: Play | J14: 122.58 | K14: 02/02 | L14: NU
I15: emprestimo | J15: 543.73 | K15: 08/18 | L15: ML
I16: capinha | J16: 14.25 | K16: 02/04 | L16: ML
I17: figurino | J17: 55.98 | K17: 02/02 | L17: ML
E18: total | F18: =SUM(F3:F17) -> 13921.32 | I18: torneiras | J18: 146.27 | K18: 03/06 | L18: ML
A19: total | B19: =SUM(B3:B18) -> 14141.03 | I19: cubas | J19: 111.2 | K19: 03/06 | L19: ML
I20: caneta | J20: 138.22 | K20: 03/06 | L20: ML
E21: Compras Recorrentes | I21: Puma | J21: 100.19 | K21: 04/10 | L21: ML
E22: todo mes é isso | I22: Controle pc | J22: 42.15 | K22: 07/08 | L22: ML
E23: Meli Plus | F23: 10 | I23: Pisos | J23: 107.91 | K23: 08/08 | L23: ML
E24: WellHub | F24: 149.9 | I24: Infra Ar | J24: 258.57 | K24: 09/10 | L24: ML
E25: Apple | F25: 59.9 | I25: total | J25: =SUM(J4:J24) -> 6067
E26: Prime sem anuncios | F26: 10
E27: Prime | F27: 16.68
E28: Google | F28: 30
E34: Total | F34: =SUM(F23:F33) -> 276.48

Sheet Agosto26
A1: Contas - saidas | E1: Entradas | I1: Compras parceladas
A2: Janeiro | C2: Status | E2: Janeiro | I2: Janeiro | N2: Totais mensal
A3: maisa | B3: 500 | E3: Salario | F3: 5300 | I3: Compra | J3: valor | K3: Parcelas | L3: Instituição | N3: saidas | Q3: previsão de sobra
A4: aP | B4: 1400 | E4: Vale | F4: 3000 | I4: pedras | J4: 783.34 | K4: 03/03 | L4: Bradesco | N4: =B19 -> 6389.03 | Q4: 0
A5: claro | B5: 159.79 | I5: carro | J5: 711.2 | K5: 03/06 | L5: bradesco | N5: Entradas
A6: Condominio | B6: 400 | I6: celular | J6: 483.89 | K6: 03/21 | L6: bradesco | N6: =F18 -> 8300
A7: CPFL | B7: 40 | I7: ML | J7: 69.25 | K7: 09/12 | L7: NU | N7: Sobrou do mes passado
A8: emprestimo | B8: 650 | I8: Prime | J8: 16.68 | K8: 05/10 | L8: NU | N8: =Julho26!Q4 -> 0
A9: iptu | B9: 110.71 | I9: Dompas | J9: 118.66 | K9: 03/03 | L9: NU | N9: Colocado na poupança
A10: cartao nu | B10: 250 | I10: emprestimo | J10: 543.73 | K10: 09/18 | L10: ML | N10: 0
A11: mercado pago | B11: 900 | I11: capinha | J11: 14.25 | K11: 03/04 | L11: ML
A12: bradesco | B12: 1978.53 | I12: torneiras | J12: 146.27 | K12: 04/06 | L12: ML
I13: cubas | J13: 111.2 | K13: 04/06 | L13: ML
I14: caneta | J14: 138.22 | K14: 04/06 | L14: ML
I15: Puma | J15: 100.19 | K15: 05/10 | L15: ML
I16: Controle pc | J16: 42.15 | K16: 08/08 | L16: ML
I17: Infra Ar | J17: 258.57 | K17: 10/10 | L17: ML
E18: total | F18: =SUM(F3:F17) -> 8300
A19: total | B19: =SUM(B3:B18) -> 6389.03
E21: Compras Recorrentes
E22: todo mes é isso
E23: Meli Plus | F23: 10
E24: WellHub | F24: 149.9
E25: Apple | F25: 59.9 | I25: total | J25: =SUM(J4:J24) -> 3537.6
E26: Prime sem anuncios | F26: 10
E27: Prime | F27: 16.68
E28: Google | F28: 30
E34: Total | F34: =SUM(F23:F33) -> 276.48

Sheet Setembro26
A1: Contas - saidas | E1: Entradas | I1: Compras parceladas
A2: Janeiro | C2: Status | E2: Janeiro | I2: Janeiro | N2: Totais mensal
A3: maisa | B3: 500 | E3: Salario | F3: 5300 | I3: Compra | J3: valor | K3: Parcelas | L3: Instituição | N3: saidas | Q3: previsão de sobra
A4: aP | B4: 1400 | E4: Vale | F4: 3000 | I4: carro | J4: 711.2 | K4: 04/06 | L4: bradesco | N4: =B19 -> 5005.7 | Q4: =N6-N4+N8+N10 -> 3294.3
A5: claro | B5: 159.79 | I5: celular | J5: 483.89 | K5: 04/21 | L5: bradesco | N5: Entradas
A6: Condominio | B6: 400 | I6: ML | J6: 69.25 | K6: 10/12 | L6: NU | N6: =F18 -> 8300
A7: CPFL | B7: 40 | I7: Prime | J7: 16.68 | K7: 06/10 | L7: NU | N7: Sobrou do mes passado
A8: emprestimo | B8: 650 | I8: emprestimo | J8: 543.73 | K8: 10/18 | L8: ML | N8: =Agosto26!Q4 -> 0
A9: iptu | B9: 110.71 | I9: capinha | J9: 14.25 | K9: 04/04 | L9: ML | N9: Colocado na poupança
A10: cartao nu | B10: 0 | I10: torneiras | J10: 146.27 | K10: 05/06 | L10: ML | N10: 0
A11: mercado pago | B11: 550 | I11: cubas | J11: 111.2 | K11: 05/06 | L11: ML
A12: bradesco | B12: 1195.2 | I12: caneta | J12: 138.22 | K12: 05/06 | L12: ML
I13: Puma | J13: 100.19 | K13: 06/10 | L13: ML
E18: total | F18: =SUM(F3:F17) -> 8300
A19: total | B19: =SUM(B3:B18) -> 5005.7
E21: Compras Recorrentes
E22: todo mes é isso
E23: Meli Plus | F23: 10 | I23: total | J23: =SUM(J4:J22) -> 2334.88
E24: WellHub | F24: 149.9
E25: Apple | F25: 59.9
E26: Prime sem anuncios | F26: 10
E27: Prime | F27: 16.68
E28: Google | F28: 30
E34: Total | F34: =SUM(F23:F33) -> 276.48

Sheet Outubro26
A1: Contas - saidas | E1: Entradas | I1: Compras parceladas
A2: Janeiro | C2: Status | E2: Janeiro | I2: Janeiro | N2: Totais mensal
A3: maisa | B3: 500 | E3: Salario | F3: 5300 | I3: Compra | J3: valor | K3: Parcelas | L3: Instituição | N3: saidas | Q3: previsão de sobra
A4: aP | B4: 1400 | E4: Vale | F4: 3136.84 | I4: carro | J4: 711.2 | K4: 06/06 | L4: bradesco | N4: =B19 -> 4955.7 | Q4: =N6-N4+N8+N10 -> 6775.44
A5: claro | B5: 159.79 | I5: celular | J5: 483.89 | K5: 05/21 | L5: bradesco | N5: Entradas
A6: Condominio | B6: 400 | I6: ML | J6: 69.25 | K6: 11/12 | L6: NU | N6: =F18 -> 8436.84
A7: CPFL | B7: 40 | I7: Prime | J7: 16.68 | K7: 07/10 | L7: NU | N7: Sobrou do mes passado
A8: emprestimo | B8: 650 | I8: emprestimo | J8: 543.73 | K8: 11/18 | L8: ML | N8: =Setembro26!Q4 -> 3294.3
A9: iptu | B9: 110.71 | I9: torneiras | J9: 146.27 | K9: 06/06 | L9: ML | N9: Colocado na poupança
A10: cartao nu | B10: 0 | I10: cubas | J10: 111.2 | K10: 06/06 | L10: ML | N10: 0
A11: mercado pago | B11: 500 | I11: caneta | J11: 138.22 | K11: 06/06 | L11: ML
A12: bradesco | B12: 1195.2 | I12: Puma | J12: 100.19 | K12: 07/10 | L12: ML
E18: total | F18: =SUM(F3:F17) -> 8436.84
A19: total | B19: =SUM(B3:B18) -> 4955.7
E21: Compras Recorrentes
E22: todo mes é isso | I22: total | J22: =SUM(J4:J21) -> 2320.63
E23: Meli Plus | F23: 10
E24: WellHub | F24: 149.9
E25: Apple | F25: 59.9
E26: Prime sem anuncios | F26: 10
E27: Prime | F27: 16.68
E28: Google | F28: 30
E34: Total | F34: =SUM(F23:F33) -> 276.48

Sheet Novembro26
A1: Contas - saidas | E1: Entradas | I1: Compras parceladas
A2: Janeiro | C2: Status | E2: Janeiro | I2: Janeiro | N2: Totais mensal
A3: maisa | B3: 500 | E3: Salario | F3: 4500 | I3: Compra | J3: valor | K3: Parcelas | L3: Instituição | N3: saidas | Q3: previsão de sobra
A4: aP | B4: 1400 | E4: Vale | F4: 3000 | I4: celular | J4: 483.89 | K4: 06/21 | L4: bradesco | N4: =B19 -> 4644.99 | Q4: =N6-N4+N8+N10 -> 9630.45
A5: claro | B5: 159.79 | I5: ML | J5: 69.25 | K5: 12/12 | L5: NU | N5: Entradas
A6: Condominio | B6: 400 | I6: Prime | J6: 16.68 | K6: 08/10 | L6: NU | N6: =F18 -> 7500
A7: CPFL | B7: 40 | I7: emprestimo | J7: 543.73 | K7: 12/18 | L7: ML | N7: Sobrou do mes passado
A8: emprestimo | B8: 650 | I8: Puma | J8: 100.19 | K8: 08/10 | L8: ML | N8: =Outubro26!Q4 -> 6775.44
A9: cartao nu | B9: 0 | N9: Colocado na poupança
A10: mercado pago | B10: 300 | N10: 0
A11: bradesco | B11: 1195.2
E18: total | F18: =SUM(F3:F17) -> 7500
A19: total | B19: =SUM(B3:B18) -> 4644.99
E21: Compras Recorrentes
E22: todo mes é isso | I22: total | J22: =SUM(J4:J21) -> 1213.74
E23: Meli Plus | F23: 10
E24: WellHub | F24: 149.9
E25: Apple | F25: 59.9
E26: Prime sem anuncios | F26: 10
E27: Prime | F27: 16.68
E28: Google | F28: 30
E34: Total | F34: =SUM(F23:F33) -> 276.48

Sheet Dezembro26
A1: Contas - saidas | E1: Entradas | I1: Compras parceladas
A2: Janeiro | C2: Status | E2: Janeiro | I2: Janeiro | N2: Totais mensal
A3: maisa | B3: 500 | E3: Salario | F3: 4500 | I3: Compra | J3: valor | K3: Parcelas | L3: Instituição | N3: saidas | Q3: previsão de sobra
A4: aP | B4: 1400 | E4: Vale | F4: 3000 | I4: celular | J4: 483.89 | K4: 07/21 | L4: bradesco | N4: =B19 -> 3933.68 | Q4: =N6-N4+N8+N10 -> 17196.77
A5: claro | B5: 159.79 | E5: decimo | F5: 4000 | I5: Prime | J5: 16.68 | K5: 09/10 | L5: NU | N5: Entradas
A6: Condominio | B6: 400 | I6: emprestimo | J6: 543.73 | K6: 13/18 | L6: ML | N6: =F18 -> 11500
A7: CPFL | B7: 40 | I7: Puma | J7: 100.19 | K7: 09/10 | L7: ML | N7: Sobrou do mes passado
A8: emprestimo | B8: 650 | N8: =Novembro26!Q4 -> 9630.45
A9: cartao nu | B9: 0 | N9: Colocado na poupança
A10: mercado pago | B10: 300 | N10: 0
A11: bradesco | B11: 483.89
E18: total | F18: =SUM(F3:F17) -> 11500
A19: total | B19: =SUM(B3:B18) -> 3933.68
E21: Compras Recorrentes
E22: todo mes é isso | I22: total | J22: =SUM(J4:J21) -> 1144.49
E23: Meli Plus | F23: 10
E24: WellHub | F24: 149.9
E25: Apple | F25: 59.9
E26: Prime sem anuncios | F26: 10
E27: Prime | F27: 16.68
E28: Google | F28: 30
E34: Total | F34: =SUM(F23:F33) -> 276.48

Sheet Janeiro27
A1: Contas - saidas | E1: Entradas | I1: Compras parceladas
A2: Janeiro | C2: Status | E2: Janeiro | I2: Janeiro | N2: Totais mensal
A3: maisa | B3: 500 | E3: Salario | F3: 4500 | I3: Compra | J3: valor | K3: Parcelas | L3: Instituição | N3: saidas | Q3: previsão de sobra
A4: aP | B4: 1400 | E4: Vale | F4: 3136.84 | I4: celular | J4: 483.89 | K4: 08/21 | L4: bradesco | N4: =B19 -> 3933.68 | Q4: =N6-N4+N8+N10 -> 20899.93
A5: claro | B5: 159.79 | I5: Prime | J5: 16.68 | K5: 10/10 | L5: NU | N5: Entradas
A6: Condominio | B6: 400 | I6: emprestimo | J6: 543.73 | K6: 14/18 | L6: ML | N6: =F18 -> 7636.84
A7: CPFL | B7: 40 | I7: Puma | J7: 100.19 | K7: 10/10 | L7: ML | N7: Sobrou do mes passado
A8: emprestimo | B8: 650 | N8: =Dezembro26!Q4 -> 17196.77
A9: cartao nu | B9: 0 | N9: Colocado na poupança
A10: mercado pago | B10: 300 | N10: 0
A11: bradesco | B11: 483.89
E18: total | F18: =SUM(F3:F17) -> 7636.84 | I18: total | J18: =SUM(J4:J13) -> 1144.49
A19: total | B19: =SUM(B3:B18) -> 3933.68
E21: Compras Recorrentes
E22: todo mes é isso
E34: Total | F34: =SUM(F23:F33) -> 0

Sheet Fevereiro27
A1: Contas - saidas | E1: Entradas | I1: Compras parceladas
A2: Janeiro | C2: Status | E2: Janeiro | I2: Janeiro | N2: Totais mensal
A3: aP | B3: 1400 | E3: Salario | F3: 4500 | I3: Compra | J3: valor | K3: Parcelas | L3: Instituição | N3: saidas | Q3: previsão de sobra
A4: claro | B4: 159.79 | E4: Vale | F4: 3136.84 | I4: celular | J4: 483.89 | K4: 09/21 | L4: bradesco | N4: =B19 -> 2783.68 | Q4: =N6-N4+N8+N10 -> 25753.09
A5: Condominio | B5: 400 | I5: emprestimo | J5: 543.73 | K5: 15/18 | L5: ML | N5: Entradas
A6: CPFL | B6: 40 | N6: =F18 -> 7636.84
A7: cartao nu | B7: 0 | N7: Sobrou do mes passado
A8: mercado pago | B8: 300 | N8: =Janeiro27!Q4 -> 20899.93
A9: bradesco | B9: 483.89 | N9: Colocado na poupança
N10: 0
E18: total | F18: =SUM(F3:F17) -> 7636.84 | I18: total | J18: =SUM(J4:J13) -> 1027.62
A19: total | B19: =SUM(B3:B18) -> 2783.68
E21: Compras Recorrentes
E22: todo mes é isso
E34: Total | F34: =SUM(F23:F33) -> 0

Sheet Março27
A1: Contas - saidas | E1: Entradas | I1: Compras parceladas
A2: Janeiro | C2: Status | E2: Janeiro | I2: Janeiro | N2: Totais mensal
A3: aP | B3: 1400 | E3: Salario | F3: 4500 | I3: Compra | J3: valor | K3: Parcelas | L3: Instituição | N3: saidas | Q3: previsão de sobra
A4: claro | B4: 159.79 | E4: Vale | F4: 3136.84 | I4: emprestimo | J4: 543.73 | K4: 16/18 | L4: ML | N4: =B19 -> 2483.68 | Q4: =N6-N4+N8+N10 -> 30906.25
A5: Condominio | B5: 400 | I5: celular | J5: 483.89 | K5: 10/21 | L5: bradesco | N5: Entradas
A6: CPFL | B6: 40 | N6: =F18 -> 7636.84
A7: Cartao Nu | B7: 0 | N7: Sobrou do mes passado
A8: Cartao Bradesco | B8: 483.89 | N8: =Fevereiro27!Q4 -> 25753.09
A9: Cartao ML | B9: 0 | N9: Colocado na poupança
N10: 0
E18: total | F18: =SUM(F3:F17) -> 7636.84 | I18: total | J18: =SUM(J4:J13) -> 1027.62
A19: total | B19: =SUM(B3:B18) -> 2483.68
E21: Compras Recorrentes
E22: todo mes é isso
E34: Total | F34: =SUM(F23:F33) -> 0

Sheet Abril27
A1: Contas - saidas | E1: Entradas | I1: Compras parceladas
A2: Janeiro | C2: Status | E2: Janeiro | I2: Janeiro | N2: Totais mensal
A3: aP | B3: 1400 | E3: Salario | F3: 4500 | I3: Compra | J3: valor | K3: Parcelas | L3: Instituição | N3: saidas | Q3: previsão de sobra
A4: claro | B4: 159.79 | E4: Vale | F4: 3136.84 | I4: emprestimo | J4: 543.73 | K4: 17/18 | L4: ML | N4: =B19 -> 2483.68 | Q4: =N6-N4+N8+N10 -> 40726.59
A5: Condominio | B5: 400 | E5: PLR | F5: 4667.18 | I5: celular | J5: 483.89 | K5: 11/21 | L5: bradesco | N5: Entradas
A6: CPFL | B6: 40 | N6: =F18 -> 12304.02
A7: Cartao Nu | B7: 0 | N7: Sobrou do mes passado
A8: Cartao Bradesco | B8: 483.89 | N8: ='Março27'!Q4 -> 30906.25
A9: Cartao ML | B9: 0 | N9: Colocado na poupança
N10: 0
E18: total | F18: =SUM(F3:F17) -> 12304.02 | I18: total | J18: =SUM(J4:J13) -> 1027.62
A19: total | B19: =SUM(B3:B18) -> 2483.68
E21: Compras Recorrentes
E22: todo mes é isso
E34: Total | F34: =SUM(F23:F33) -> 0

Sheet Maio27
A1: Contas - saidas | E1: Entradas | I1: Compras parceladas
A2: Janeiro | C2: Status | E2: Janeiro | I2: Janeiro | N2: Totais mensal
A3: aP | B3: 1400 | E3: Salario | F3: 4500 | I3: Compra | J3: valor | K3: Parcelas | L3: Instituição | N3: saidas | Q3: previsão de sobra
A4: claro | B4: 159.79 | E4: Vale | F4: 3136.84 | I4: emprestimo | J4: 543.73 | K4: 18/18 | L4: ML | N4: =B19 -> 2483.68 | Q4: =N6-N4+N8+N10 -> 50546.93
A5: Condominio | B5: 400 | E5: PLR | F5: 4667.18 | I5: celular | J5: 483.89 | K5: 12/21 | L5: bradesco | N5: Entradas
A6: CPFL | B6: 40 | N6: =F18 -> 12304.02
A7: Cartao Nu | B7: 0 | N7: Sobrou do mes passado
A8: Cartao Bradesco | B8: 483.89 | N8: =Abril27!Q4 -> 40726.59
A9: Cartao ML | B9: 0 | N9: Colocado na poupança
N10: 0
E18: total | F18: =SUM(F3:F17) -> 12304.02 | I18: total | J18: =SUM(J4:J13) -> 1027.62
A19: total | B19: =SUM(B3:B18) -> 2483.68
E21: Compras Recorrentes
E22: todo mes é isso
E34: Total | F34: =SUM(F23:F33) -> 0
